epconversions/__init__.py
epconversions/ec.py
epconversions/epconversions.py
epconversions-0.2.2.dist-info/AUTHORS.rst
epconversions-0.2.2.dist-info/LICENSE
epconversions-0.2.2.dist-info/METADATA
epconversions-0.2.2.dist-info/WHEEL
epconversions-0.2.2.dist-info/top_level.txt
epconversions-0.2.2.dist-info/RECORD
