Metadata-Version: 2.1
Name: epconversions
Version: 0.2.2
Summary: Unit conversions for E+
Home-page: https://github.com/pyenergyplus/epconversions
Author: Santosh Philip
Author-email: santosh@noemail.com
License: MIT license
Keywords: epconversions
Classifier: Development Status :: 2 - Pre-Alpha
Classifier: Intended Audience :: Developers
Classifier: License :: OSI Approved :: Mozilla Public License 2.0 (MPL 2.0)
Classifier: Natural Language :: English
Classifier: Programming Language :: Python :: 3
Classifier: Programming Language :: Python :: 3.9
Classifier: Programming Language :: Python :: 3.10
Classifier: Programming Language :: Python :: 3.11
Classifier: Programming Language :: Python :: 3.12
Requires-Python: >=3.6
License-File: LICENSE
License-File: AUTHORS.rst
